MANIFEST.in
README.rst
setup.py
rentswatch_scraper/__init__.py
rentswatch_scraper/agents.py
rentswatch_scraper/browser.py
rentswatch_scraper/db.py
rentswatch_scraper/fields.py
rentswatch_scraper/reporting.py
rentswatch_scraper/scraper.py
rentswatch_scraper/socks.py
rentswatch_scraper/version.py
rentswatch_scraper.egg-info/PKG-INFO
rentswatch_scraper.egg-info/SOURCES.txt
rentswatch_scraper.egg-info/dependency_links.txt
rentswatch_scraper.egg-info/entry_points.txt
rentswatch_scraper.egg-info/requires.txt
rentswatch_scraper.egg-info/top_level.txt