Metadata-Version: 1.1
Name: rentswatch-scraper
Version: 0.31.0
Summary: A basic framework to scrap renting ads
Home-page: https://github.com/jplusplus/rentswatch-scraper
Author: pirhoo
Author-email: hello@pirhoo.com
License: LGPL
Platform: UNKNOWN
Classifier: Development Status :: 4 - Beta
Classifier: Intended Audience :: Developers
Classifier: License :: OSI Approved :: GNU Lesser General Public License v3 (LGPLv3)
Classifier: Natural Language :: English
Classifier: Operating System :: Unix
Classifier: Programming Language :: Python :: 2.7
Classifier: Programming Language :: Python :: 3.4
Classifier: Programming Language :: Python :: Implementation :: PyPy
Classifier: Operating System :: OS Independent
